coingecko_sdk/__init__.py
coingecko_sdk/_base_client.py
coingecko_sdk/_client.py
coingecko_sdk/_compat.py
coingecko_sdk/_constants.py
coingecko_sdk/_exceptions.py
coingecko_sdk/_files.py
coingecko_sdk/_models.py
coingecko_sdk/_qs.py
coingecko_sdk/_resource.py
coingecko_sdk/_response.py
coingecko_sdk/_streaming.py
coingecko_sdk/_types.py
coingecko_sdk/_version.py
coingecko_sdk/py.typed
coingecko_sdk/_utils/__init__.py
coingecko_sdk/_utils/_compat.py
coingecko_sdk/_utils/_datetime_parse.py
coingecko_sdk/_utils/_logs.py
coingecko_sdk/_utils/_proxy.py
coingecko_sdk/_utils/_reflection.py
coingecko_sdk/_utils/_resources_proxy.py
coingecko_sdk/_utils/_streams.py
coingecko_sdk/_utils/_sync.py
coingecko_sdk/_utils/_transform.py
coingecko_sdk/_utils/_typing.py
coingecko_sdk/_utils/_utils.py
coingecko_sdk/lib/.keep
coingecko_sdk/resources/__init__.py
coingecko_sdk/resources/asset_platforms.py
coingecko_sdk/resources/entities.py
coingecko_sdk/resources/exchange_rates.py
coingecko_sdk/resources/key.py
coingecko_sdk/resources/ping.py
coingecko_sdk/resources/public_treasury.py
coingecko_sdk/resources/token_lists.py
coingecko_sdk/resources/coins/__init__.py
coingecko_sdk/resources/coins/categories.py
coingecko_sdk/resources/coins/circulating_supply_chart.py
coingecko_sdk/resources/coins/coins.py
coingecko_sdk/resources/coins/history.py
coingecko_sdk/resources/coins/list.py
coingecko_sdk/resources/coins/market_chart.py
coingecko_sdk/resources/coins/markets.py
coingecko_sdk/resources/coins/ohlc.py
coingecko_sdk/resources/coins/tickers.py
coingecko_sdk/resources/coins/top_gainers_losers.py
coingecko_sdk/resources/coins/total_supply_chart.py
coingecko_sdk/resources/coins/contract/__init__.py
coingecko_sdk/resources/coins/contract/contract.py
coingecko_sdk/resources/coins/contract/market_chart.py
coingecko_sdk/resources/derivatives/__init__.py
coingecko_sdk/resources/derivatives/derivatives.py
coingecko_sdk/resources/derivatives/exchanges.py
coingecko_sdk-1.11.3.dist-info/METADATA
coingecko_sdk-1.11.3.dist-info/WHEEL
coingecko_sdk-1.11.3.dist-info/licenses/LICENSE
coingecko_sdk-1.11.3.dist-info/RECORD
